twill_throttle/__init__.py
twill_throttle/limiter .py
twill_throttle-1.0.3.dist-info/licenses/LICENSE
twill_throttle-1.0.3.dist-info/METADATA
twill_throttle-1.0.3.dist-info/WHEEL
twill_throttle-1.0.3.dist-info/top_level.txt
twill_throttle-1.0.3.dist-info/RECORD
