Metadata-Version: 2.4
Name: twill_throttle
Version: 1.0.3
Summary: A Python rate limiter and throttling utility with async and sync support.
Author-email: Avi Twil <avitwil@gmail.com>
License: MIT
Project-URL: Homepage, https://github.com/avitwil/twill_throttle
Project-URL: Bug Tracker, https://github.com/avitwil/twill_throttle/issues
Project-URL: PyPI, https://pypi.org/project/twill_throttle/
Keywords: throttle,rate-limit,async,sync,python,utility
Classifier: Programming Language :: Python :: 3
Classifier: License :: OSI Approved :: MIT License
Classifier: Operating System :: OS Independent
Classifier: Intended Audience :: Developers
Classifier: Topic :: Software Development :: Libraries :: Python Modules
Requires-Python: >=3.8
License-File: LICENSE
Dynamic: license-file
